isabelle_client/__init__.py
isabelle_client/conftest.py
isabelle_client/data_models.py
isabelle_client/isabelle_client.py
isabelle_client/isabelle_connector.py
isabelle_client/py.typed
isabelle_client/resources/Cygwin-Isabelle.bat
isabelle_client/resources/example.txt
isabelle_client/resources/isabelle
isabelle_client/resources/isabelle-responses/cancel
isabelle_client/resources/isabelle-responses/help
isabelle_client/resources/isabelle-responses/purge_theories
isabelle_client/resources/isabelle-responses/session_build
isabelle_client/resources/isabelle-responses/session_start
isabelle_client/resources/isabelle-responses/session_stop
isabelle_client/resources/isabelle-responses/shutdown
isabelle_client/resources/isabelle-responses/unknown
isabelle_client/resources/isabelle-responses/use_theories
isabelle_client/resources/isabelle-responses/use_theories.Fail
isabelle_client/resources/isabelle-responses/use_theories.Sledgehammer
isabelle_client/socket_communication.py
isabelle_client/utils.py
isabelle_client-1.0.1.dist-info/METADATA
isabelle_client-1.0.1.dist-info/WHEEL
isabelle_client-1.0.1.dist-info/licenses/LICENSE
isabelle_client-1.0.1.dist-info/RECORD
