Metadata-Version: 2.4
Name: isabelle-client
Version: 1.0.1
Summary: A client to Isabelle proof assistant server
License-Expression: Apache-2.0
License-File: LICENSE
Keywords: TCP client,Isabelle proof assistant,interactive theorem prover
Author: Boris Shminke
Author-email: <boris@shminke.com
Requires-Python: >= 3.10, < 3.15
Classifier: Programming Language :: Python :: 3.14
Classifier: Programming Language :: Python :: 3.13
Classifier: Programming Language :: Python :: 3.12
Classifier: Programming Language :: Python :: 3.11
Classifier: Programming Language :: Python :: 3.10
Classifier: Operating System :: OS Independent
Classifier: Intended Audience :: Science/Research
Classifier: Development Status :: 4 - Beta
Classifier: Environment :: Console
Classifier: Natural Language :: English
Classifier: Topic :: Scientific/Engineering :: Artificial Intelligence
Classifier: Typing :: Typed
Provides-Extra: dev
Provides-Extra: doc
Provides-Extra: test
Requires-Dist: coverage ; extra == "test"
Requires-Dist: debugpy ; extra == "dev"
Requires-Dist: furo ; extra == "doc"
Requires-Dist: isort ; extra == "dev"
Requires-Dist: jedi-language-server ; extra == "dev"
Requires-Dist: pre-commit ; extra == "dev"
Requires-Dist: pydantic
Requires-Dist: pydoclint ; extra == "dev"
Requires-Dist: pyrefly ; extra == "dev"
Requires-Dist: pyroma ; extra == "dev"
Requires-Dist: pytest ; extra == "test"
Requires-Dist: ruff ; extra == "dev"
Requires-Dist: sphinx-autodoc-typehints ; extra == "doc"
Requires-Dist: tbump ; extra == "dev"
Requires-Dist: toml ; extra == "dev"
Requires-Dist: tox ; extra == "dev"
Project-URL: Homepage, https://github.com/inpefess/isabelle-client
Project-URL: Issues, https://github.com/inpefess/isabelle-client/issues
Project-URL: Repository, https://github.com/inpefess/isabelle-client.git
